perceptronpkg/__init__.py
perceptronpkg/perceptron.py
perceptron_pypi_saiprasad_reddy-0.0.2.dist-info/LICENSE
perceptron_pypi_saiprasad_reddy-0.0.2.dist-info/METADATA
perceptron_pypi_saiprasad_reddy-0.0.2.dist-info/WHEEL
perceptron_pypi_saiprasad_reddy-0.0.2.dist-info/top_level.txt
perceptron_pypi_saiprasad_reddy-0.0.2.dist-info/RECORD
