Metadata-Version: 2.1
Name: perceptron-pypi-saiprasad-reddy
Version: 0.0.2
Summary: Its an implementation of perceptron
Home-page: https://github.com/saiprasad-reddy/perceptron_pypi
Author: saiprasad reddy
Author-email: saiprasadreddy@gmail.com
License: UNKNOWN
Project-URL: Bug Tracker, https://github.com/{USER_NAME}/{PROJECT_NAME}/issues
Platform: UNKNOWN
Classifier: Programming Language :: Python :: 3
Classifier: License :: OSI Approved :: MIT License
Classifier: Operating System :: OS Independent
Requires-Python: >=3.7
License-File: LICENSE
Requires-Dist: numpy
Requires-Dist: tqdm
